{
    "xmlns:xmlref": "http://bwt/xmlref",
    "crew": {
        "commander": "radioman",
        "driver": null,
        "gunner": null,
        "loader": null
    },
    "supplySlots": [
        4.0,
        1.0,
        1.0,
        6.0,
        6.0,
        6.0,
        7.0,
        8.0,
        8.0,
        8.0
    ],
    "postProgressionTree": "role_ATSPG_assault",
    "customRoleSlotOptions": [
        3.0,
        5.0
    ],
    "speedLimits": {
        "forward": 35,
        "backward": 12
    },
    "invisibility": {
        "moving": 0.135,
        "still": 0.226,
        "camouflageBonus": 0.04,
        "firePenalty": 0.339
    },
    "optDevsOverrides": {
        "camouflageNet": {
            "invisibilityBonus": [
                0.15,
                0.175
            ]
        },
        "additionalInvisibilityDevice": {
            "invisibilityBonus": [
                0.05,
                0.06
            ]
        },
        "trophyBasicAdditionalInvisibilityDevice": {
            "invisibilityBonus": 0.05
        },
        "trophyUpgradedAdditionalInvisibilityDevice": {
            "invisibilityBonus": 0.07
        }
    },
    "repairCost": 9.2,
    "premiumVehicleXPFactor": 0.05,
    "crewXpFactor": 1.5,
    "camouflage": {
        "priceFactor": 1.8
    },
    "hull": {
        "armor": {
            "armor_1": 120,
            "armor_2": 120,
            "armor_3": 80,
            "armor_4": 50,
            "armor_5": 45,
            "armor_6": 50,
            "armor_7": 80,
            "armor_8": 0,
            "armor_9": 60,
            "armor_10": 20,
            "armor_11": 40,
            "armor_12": {
                "vehicleDamageFactor": 0
            },
            "armor_13": 50,
            "armor_14": 100,
            "armor_15": 160,
            "armor_16": 130
        },
        "primaryArmor": [
            "armor_1",
            "armor_3",
            "armor_11"
        ],
        "weight": 32470,
        "maxHealth": 1520,
        "ammoBayHealth": {
            "maxHealth": 260,
            "maxRegenHealth": 180,
            "repairCost": 1.0
        },
        "models": {
            "undamaged": "vehicles/american/A151_TS_60/normal/lod0/Hull.model",
            "destroyed": "vehicles/american/A151_TS_60/crash/lod0/Hull.model",
            "exploded": "vehicles/american/A151_TS_60/crash/lod0/Hull.model"
        },
        "swinging": {
            "lodDist": "FAR",
            "pitchParams": [
                0.34,
                38.0,
                0.36,
                1.0,
                0.05,
                0.34
            ],
            "rollParams": [
                1.0,
                0.34,
                38.0,
                0.36,
                1.0,
                0.06,
                0.4
            ],
            "sensitivityToImpulse": 0.24
        },
        "exhaust": {
            "pixie": "diesel_large",
            "nodes": [
                "HP_Track_Exhaus_1",
                "HP_Track_Exhaus_2"
            ]
        },
        "turretPositions": {
            "turret": [
                0.0,
                0.728417,
                -1.57917
            ]
        },
        "hitTester": {
            "collisionModelServer": "vehicles/american/A151_TS_60/collision/Hull.model",
            "collisionModelClient": "vehicles/american/A151_TS_60/collision_client/Hull.model"
        },
        "hangarShadowTexture": "vehicles/american/A151_TS_60/TS_60_HangarShadowMap.dds",
        "customizationSlots": {
            "slot": {
                "slotType": "projectionDecal",
                "slotId": 15063,
                "tags": [
                    "formfactor_rect1x2",
                    "mimic",
                    "front"
                ],
                "position": [
                    1e-05,
                    1.42957,
                    2.92628
                ],
                "rotation": [
                    0.347484,
                    5.7e-05,
                    3.13981
                ],
                "scale": [
                    2.17859,
                    0.26688,
                    2.17859
                ],
                "hiddenForUser": "true",
                "showOn": 16,
                "anchorShift": -0.03
            }
        },
        "customization": {
            "customizableVehicleAreas": {
                "paint": "HULL",
                "camouflage": "HULL"
            }
        },
        "camouflage": {
            "density": [
                101.406,
                101.408
            ],
            "aoTextureSize": [
                1024.0,
                1024.0
            ]
        }
    },
    "chassis": {
        "Chassis_A151_TS_60": {
            "userString": "#usa_vehicles:Chassis_A151_TS_60",
            "tags": [],
            "level": 8,
            "price": 30000,
            "notInShop": "true",
            "armor": {
                "leftTrack": 20,
                "rightTrack": 20
            },
            "weight": 8861,
            "maxLoad": 65000,
            "terrainResistance": [
                1.1,
                1.4,
                2.9
            ],
            "brakeForce": 60000,
            "rotationIsAroundCenter": "true",
            "rotationSpeed": 28,
            "shotDispersionFactors": {
                "vehicleMovement": 0.25,
                "vehicleRotation": 0.25
            },
            "bulkHealthFactor": 3.0,
            "maxHealth": 230,
            "maxRegenHealth": 175,
            "repairCost": 5.0,
            "models": {
                "undamaged": "vehicles/american/A151_TS_60/normal/lod0/Chassis.model",
                "destroyed": "vehicles/american/A151_TS_60/crash/lod0/Chassis.model",
                "exploded": "vehicles/american/A151_TS_60/crash/lod0/Chassis.model"
            },
            "traces": {
                "lodDist": "MEDIUM",
                "bufferPrefs": "largeTank",
                "textureSet": "usa_01",
                "size": [
                    0.5,
                    0.71
                ]
            },
            "tracks": {
                "lodDist": "MEDIUM_TRACK",
                "trackPair": {
                    "trackPairIdx": 0,
                    "leftMaterial": "track_mat_L_skinned",
                    "rightMaterial": "track_mat_R_skinned",
                    "textureScale": -1.8,
                    "trackDebris": {
                        "isLeft": "false",
                        "destructionEffect": null,
                        "physicalParams": {
                            "renderModelOffset": -0.045563,
                            "interpolationsCount": 1,
                            "lengthwiseSpringLength": 0.085568,
                            "widthwiseSpringLength": 0.427379,
                            "hingeJointStiffness": 1322.298706,
                            "torsionStiffnessStep": 7,
                            "wheelGroups": {
                                "wheelGroup": {
                                    "wheelName": "WD_R0",
                                    "groupRadius": 0.269424,
                                    "groupInnerOffset": -0.366495,
                                    "groupOuterOffset": 0.266495
                                }
                            },
                            "hullCollider": {
                                "boxCollider": {
                                    "row0": [
                                        3.35314,
                                        0.0,
                                        -1e-06
                                    ],
                                    "row1": [
                                        0.0,
                                        0.260896,
                                        -0.1481
                                    ],
                                    "row2": [
                                        0.0,
                                        0.354204,
                                        0.623972
                                    ],
                                    "row3": [
                                        0.0,
                                        1.257483,
                                        -2.793522
                                    ]
                                }
                            }
                        }
                    }
                }
            },
            "AODecals": {
                "decal": {
                    "transform": {
                        "row0": [
                            4.53902,
                            0.0,
                            0.0
                        ],
                        "row1": [
                            0.0,
                            1.34202,
                            0.0
                        ],
                        "row2": [
                            0.0,
                            0.0,
                            8.63308
                        ],
                        "row3": [
                            0.0,
                            0.0,
                            0.0
                        ]
                    }
                }
            },
            "wheels": {
                "lodDist": "MEDIUM",
                "wheel": {
                    "isLeft": "true",
                    "isLeading": "true",
                    "name": "WD_L1",
                    "radius": 0.39,
                    "syncAngle": 30
                },
                "group": {
                    "isLeft": "true",
                    "template": "W_L",
                    "radius": 0.39,
                    "startIndex": 0,
                    "count": 5
                }
            },
            "drivingWheels": [
                "WD_L0",
                "WD_L1"
            ],
            "effects": {
                "lodDist": "MEDIUM",
                "mud": "largeTankMud"
            },
            "wwsoundPC": "treads_type_pc",
            "wwsoundNPC": "trds_chf_npc",
            "hullPosition": [
                0.0,
                0.875211,
                0.0
            ],
            "hitTester": {
                "collisionModelServer": "vehicles/american/A151_TS_60/collision/Chassis.model",
                "collisionModelClient": "vehicles/american/A151_TS_60/collision_client/Chassis.model"
            },
            "topRightCarryingPoint": [
                1.41007,
                2.32209
            ],
            "maxClimbAngle": 25,
            "navmeshGirth": 6.0,
            "groundNodes": {
                "group": {
                    "template": "Track_R",
                    "startIndex": 0,
                    "count": 6,
                    "isLeft": "false",
                    "minOffset": -0.1,
                    "maxOffset": 0.03
                }
            },
            "trackThickness": -0.0043,
            "trackNodes": {
                "enable": "true",
                "linkBones": "true",
                "maxAmplitude": 0.05,
                "maxOffset": 0.05,
                "gravity": -9.8,
                "elasticity": 1100,
                "damping": 2,
                "node": {
                    "isLeft": "false",
                    "name": "Track_VT_R10",
                    "forwardElastK": 0.827377,
                    "backwardElastK": 0.637213,
                    "offset": -0.058,
                    "leftSibling": "Track_VT_R9"
                }
            },
            "splineDesc": {
                "trackPair": {
                    "trackPairIdx": 0,
                    "segmentModelLeft": "vehicles/american/A151_TS_60/track/segment_01.model",
                    "segmentModelRight": "vehicles/american/A151_TS_60/track/segment_01.model",
                    "segment2ModelLeft": "vehicles/american/A151_TS_60/track/segment_02.model",
                    "segment2ModelRight": "vehicles/american/A151_TS_60/track/segment_02.model",
                    "left": "vehicles/american/A151_TS_60/track/left.track",
                    "right": "vehicles/american/A151_TS_60/track/right.track",
                    "segmentLength": 0.174329,
                    "segmentOffset": 0.279,
                    "segment2Offset": 0.085294,
                    "atlas": {
                        "UTiles": 1,
                        "VTiles": 1
                    }
                },
                "lodDist": "SPLINE_TRACK"
            },
            "physicalTracks": {
                "left": {
                    "segmentsCount": 164,
                    "segmentsOuterThickness": 0.096156,
                    "segmentsInnerThickness": 0.009455,
                    "segmentsPlaneOffset": -1.41,
                    "springsLength": {
                        "backwardMovement": {
                            "back": 0.060622,
                            "top": 0.084975,
                            "front": 0.080934,
                            "bottom": 0.067652
                        },
                        "forwardMovement": {
                            "back": 0.060622,
                            "top": 0.080175,
                            "front": 0.086012,
                            "bottom": 0.069122
                        }
                    },
                    "mainSegment": {
                        "model": "vehicles/american/A151_TS_60/track/segment_01.model",
                        "length": 0.085091
                    },
                    "secSegment": {
                        "model": "vehicles/american/A151_TS_60/track/segment_02.model",
                        "length": 0.085364
                    },
                    "collisionHull": {
                        "bottom": null,
                        "top": {
                            "part": {
                                "xStart": -3.01128,
                                "xStep": 0.042545,
                                "ySamples": [
                                    0.89525,
                                    0.918316,
                                    0.941383,
                                    0.964449,
                                    0.987515,
                                    1.01058,
                                    1.03365,
                                    1.05671,
                                    1.07978,
                                    1.10285,
                                    1.12377,
                                    1.11417,
                                    1.11417,
                                    1.11417,
                                    1.11417,
                                    1.12377,
                                    1.12377,
                                    1.12377,
                                    1.12377,
                                    1.12377,
                                    1.12377,
                                    1.12377,
                                    1.12377,
                                    1.12377,
                                    1.12377,
                                    1.12377,
                                    1.12377,
                                    1.12377,
                                    1.12374,
                                    1.12369,
                                    1.12363,
                                    1.12358,
                                    1.12352,
                                    1.12347,
                                    1.12341,
                                    1.12336,
                                    1.1233,
                                    1.12325,
                                    1.12319,
                                    1.12354,
                                    1.12375,
                                    1.12376,
                                    1.12377,
                                    1.12377,
                                    1.12377,
                                    1.12377,
                                    1.12377,
                                    1.12377,
                                    1.12377,
                                    1.12377,
                                    1.12377,
                                    1.12377,
                                    1.12377,
                                    1.12377,
                                    1.11417,
                                    1.11417,
                                    1.11417,
                                    1.12377,
                                    1.12377,
                                    1.12377,
                                    1.12377,
                                    1.12377,
                                    1.12377,
                                    1.12377,
                                    1.12377,
                                    1.12377,
                                    1.12377,
                                    1.12377,
                                    1.12377,
                                    1.12377,
                                    1.12377,
                                    1.12377,
                                    1.12377,
                                    1.12377,
                                    1.12377,
                                    1.12377,
                                    1.12377,
                                    1.12377,
                                    1.12377,
                                    1.12377,
                                    1.12377,
                                    1.12377,
                                    1.12377,
                                    1.12377,
                                    1.12377,
                                    1.12377,
                                    1.11417,
                                    1.11417,
                                    1.11417,
                                    1.12377,
                                    1.12377,
                                    1.12377,
                                    1.12377,
                                    1.12377,
                                    1.12377,
                                    1.12377,
                                    1.12377,
                                    1.12377,
                                    1.12377,
                                    1.12377,
                                    1.12377,
                                    1.12377,
                                    1.12377,
                                    1.12377,
                                    1.12377,
                                    1.12377,
                                    1.12377,
                                    1.12377,
                                    1.12377,
                                    1.12377,
                                    1.12377,
                                    1.12377,
                                    1.12377,
                                    1.12377,
                                    1.12377,
                                    1.12377,
                                    1.12377,
                                    1.12377,
                                    1.12377,
                                    1.12377,
                                    1.12377,
                                    1.12377,
                                    1.12377,
                                    1.12377,
                                    1.11417,
                                    1.11417,
                                    1.11417,
                                    1.11417,
                                    1.12377,
                                    1.12377,
                                    1.12377,
                                    1.12377,
                                    1.12377,
                                    1.12377,
                                    1.12377,
                                    1.12377,
                                    1.12377,
                                    1.12377,
                                    1.12377,
                                    1.12377,
                                    1.12377,
                                    1.12377,
                                    1.12377,
                                    1.12377,
                                    1.12377,
                                    1.12377,
                                    1.12377,
                                    1.12377,
                                    1.12377,
                                    1.12377,
                                    1.12377,
                                    1.10948,
                                    1.09434,
                                    1.07919,
                                    1.06404,
                                    1.04889,
                                    1.03375,
                                    0.979644,
                                    0.918705
                                ]
                            }
                        }
                    },
                    "bottomWheels": {
                        "wheel": "WD_L0"
                    },
                    "snapWheels": {
                        "topFront": {
                            "wheelName": "WD_L0",
                            "basePos": [
                                3.34904,
                                0.661114
                            ],
                            "shiftVec": [
                                0.264508,
                                0.079584
                            ],
                            "jointIdx": 17
                        },
                        "topBack": {
                            "wheelName": "WD_L1",
                            "basePos": [
                                -2.6087,
                                0.481886
                            ],
                            "shiftVec": [
                                -0.400422,
                                0.04573
                            ],
                            "jointIdx": 97
                        },
                        "bottomBack": {
                            "wheelName": "W_L4",
                            "basePos": [
                                -1.5466,
                                0.472795
                            ],
                            "shiftVec": [
                                0.007573,
                                -0.399455
                            ],
                            "jointIdx": 117
                        },
                        "bottomFront": {
                            "wheelName": "W_L0",
                            "basePos": [
                                2.44816,
                                0.472795
                            ],
                            "shiftVec": [
                                0.006611,
                                -0.3994
                            ],
                            "jointIdx": 0
                        }
                    },
                    "radiusOverrides": {
                        "wheel": {
                            "name": "WD_L0",
                            "radius": 0.274109
                        }
                    },
                    "teethSyncs": {
                        "syncWithMainModel": "true",
                        "segmentSyncPivotOffset": 0,
                        "sync": {
                            "name": "WD_L0",
                            "startAngle": 0.276213,
                            "teethCount": 10
                        }
                    },
                    "sourceCollisionHullPoints": {
                        "top": {
                            "range": {
                                "point": [
                                    -1.41157,
                                    1.03647,
                                    3.71089
                                ]
                            }
                        }
                    },
                    "trackPairIdx": 0
                },
                "right": {
                    "segmentsCount": 166,
                    "segmentsOuterThickness": 0.098368,
                    "segmentsInnerThickness": 0.007243,
                    "segmentsPlaneOffset": 1.41,
                    "springsLength": {
                        "backwardMovement": {
                            "back": 0.060631,
                            "top": 0.085046,
                            "front": 0.079381,
                            "bottom": 0.068041
                        },
                        "forwardMovement": {
                            "back": 0.060631,
                            "top": 0.081152,
                            "front": 0.086012,
                            "bottom": 0.067833
                        }
                    },
                    "mainSegment": {
                        "model": "vehicles/american/A151_TS_60/track/segment_01.model",
                        "length": 0.085905
                    },
                    "secSegment": {
                        "model": "vehicles/american/A151_TS_60/track/segment_02.model",
                        "length": 0.084429
                    },
                    "collisionHull": {
                        "bottom": null,
                        "top": {
                            "part": {
                                "xStart": -3.01128,
                                "xStep": 0.042545,
                                "ySamples": [
                                    0.895226,
                                    0.918296,
                                    0.941357,
                                    0.964426,
                                    0.987487,
                                    1.01056,
                                    1.03363,
                                    1.05668,
                                    1.07976,
                                    1.10283,
                                    1.12375,
                                    1.11415,
                                    1.11415,
                                    1.11415,
                                    1.11415,
                                    1.12375,
                                    1.12375,
                                    1.12375,
                                    1.12375,
                                    1.12375,
                                    1.12375,
                                    1.12375,
                                    1.12375,
                                    1.12375,
                                    1.12375,
                                    1.12375,
                                    1.12375,
                                    1.12375,
                                    1.12371,
                                    1.12365,
                                    1.1236,
                                    1.12354,
                                    1.12349,
                                    1.12343,
                                    1.12338,
                                    1.12333,
                                    1.12327,
                                    1.12322,
                                    1.12316,
                                    1.12351,
                                    1.12372,
                                    1.12373,
                                    1.12373,
                                    1.12375,
                                    1.12375,
                                    1.12375,
                                    1.12375,
                                    1.12375,
                                    1.12375,
                                    1.12375,
                                    1.12375,
                                    1.12375,
                                    1.12375,
                                    1.12375,
                                    1.11415,
                                    1.11415,
                                    1.11415,
                                    1.12375,
                                    1.12375,
                                    1.12375,
                                    1.12375,
                                    1.12375,
                                    1.12375,
                                    1.12375,
                                    1.12375,
                                    1.12375,
                                    1.12375,
                                    1.12375,
                                    1.12375,
                                    1.12375,
                                    1.12375,
                                    1.12375,
                                    1.12375,
                                    1.12375,
                                    1.12375,
                                    1.12375,
                                    1.12375,
                                    1.12375,
                                    1.12375,
                                    1.12375,
                                    1.12375,
                                    1.12375,
                                    1.12375,
                                    1.12375,
                                    1.12375,
                                    1.12375,
                                    1.11415,
                                    1.11415,
                                    1.11415,
                                    1.12375,
                                    1.12375,
                                    1.12375,
                                    1.12375,
                                    1.12375,
                                    1.12375,
                                    1.12374,
                                    1.12374,
                                    1.12374,
                                    1.12375,
                                    1.12375,
                                    1.12375,
                                    1.12375,
                                    1.12375,
                                    1.12375,
                                    1.12375,
                                    1.12375,
                                    1.12375,
                                    1.12375,
                                    1.12375,
                                    1.12375,
                                    1.12375,
                                    1.12375,
                                    1.12375,
                                    1.12375,
                                    1.12375,
                                    1.12375,
                                    1.12375,
                                    1.12375,
                                    1.12375,
                                    1.12375,
                                    1.12375,
                                    1.12375,
                                    1.12375,
                                    1.12375,
                                    1.11415,
                                    1.11415,
                                    1.11415,
                                    1.11415,
                                    1.12375,
                                    1.12375,
                                    1.12375,
                                    1.12375,
                                    1.12375,
                                    1.12375,
                                    1.12375,
                                    1.12375,
                                    1.12375,
                                    1.12375,
                                    1.12375,
                                    1.12375,
                                    1.12375,
                                    1.12375,
                                    1.12375,
                                    1.12375,
                                    1.12375,
                                    1.12375,
                                    1.12375,
                                    1.12375,
                                    1.12375,
                                    1.12375,
                                    1.12375,
                                    1.10945,
                                    1.0943,
                                    1.07916,
                                    1.06401,
                                    1.04886,
                                    1.03371,
                                    0.979615,
                                    0.918676
                                ]
                            }
                        }
                    },
                    "bottomWheels": {
                        "wheel": "WD_R0"
                    },
                    "snapWheels": {
                        "topFront": {
                            "wheelName": "WD_R0",
                            "basePos": [
                                3.34904,
                                0.661114
                            ],
                            "shiftVec": [
                                0.263142,
                                0.085443
                            ],
                            "jointIdx": 18
                        },
                        "topBack": {
                            "wheelName": "WD_R1",
                            "basePos": [
                                -2.70698,
                                0.48186
                            ],
                            "shiftVec": [
                                -0.398381,
                                0.042424
                            ],
                            "jointIdx": 99
                        },
                        "bottomBack": {
                            "wheelName": "W_R4",
                            "basePos": [
                                -1.64488,
                                0.472769
                            ],
                            "shiftVec": [
                                0.016208,
                                -0.397243
                            ],
                            "jointIdx": 119
                        },
                        "bottomFront": {
                            "wheelName": "W_R0",
                            "basePos": [
                                2.34988,
                                0.472769
                            ],
                            "shiftVec": [
                                0.018615,
                                -0.396806
                            ],
                            "jointIdx": 0
                        }
                    },
                    "radiusOverrides": {
                        "wheel": {
                            "name": "WD_R0",
                            "radius": 0.274561
                        }
                    },
                    "teethSyncs": {
                        "syncWithMainModel": "true",
                        "segmentSyncPivotOffset": 0,
                        "sync": {
                            "name": "WD_R0",
                            "startAngle": 0.282289,
                            "teethCount": 10
                        }
                    },
                    "sourceCollisionHullPoints": {
                        "top": {
                            "range": {
                                "point": [
                                    1.41157,
                                    1.03647,
                                    3.71089
                                ]
                            }
                        }
                    },
                    "trackPairIdx": 0
                }
            },
            "customizationSlots": {
                "slot": {
                    "slotType": "style",
                    "slotId": 29000,
                    "anchorPosition": [
                        -0.0,
                        2.60522,
                        -1.57917
                    ],
                    "anchorDirection": [
                        0.0,
                        1.0,
                        0.0
                    ]
                }
            },
            "customization": {
                "customizableVehicleAreas": {
                    "paint": "CHASSIS",
                    "camouflage": null
                }
            },
            "repairTime": 6.85714293
        }
    },
    "turrets0": {
        "Turret_1_A151_TS_60": {
            "userString": "#usa_vehicles:Turret_1_A151_TS_60",
            "tags": [],
            "level": 8,
            "price": 32000,
            "notInShop": "true",
            "armor": {
                "armor_1": 300,
                "armor_2": 185,
                "armor_3": 80,
                "armor_4": 60,
                "armor_5": 40,
                "armor_6": 100,
                "armor_7": 100,
                "armor_8": 0,
                "armor_9": 100,
                "armor_10": 25,
                "armor_11": 40,
                "armor_12": 60,
                "armor_13": 50,
                "armor_14": 50,
                "armor_15": 40,
                "armor_16": 100,
                "armor_17": 100,
                "armor_18": 200,
                "armor_19": 150,
                "armor_20": 145,
                "armor_21": 100,
                "armor_22": 95,
                "armor_23": 55,
                "armor_24": 75,
                "armor_25": 95,
                "armor_26": 150,
                "armor_27": 250
            },
            "primaryArmor": [
                "armor_1",
                "armor_3",
                "armor_4"
            ],
            "weight": 10000,
            "maxHealth": 380,
            "rotationSpeed": 18,
            "turretRotatorHealth": {
                "maxHealth": 160,
                "maxRegenHealth": 80,
                "repairCost": 1.0
            },
            "circularVisionRadius": 380,
            "surveyingDeviceHealth": {
                "maxHealth": 110,
                "maxRegenHealth": 55,
                "repairCost": 1.0
            },
            "guns": {
                "_120mm_T123E2_SPG": {
                    "maxAmmo": 40,
                    "armor": {
                        "armor_1": {
                            "vehicleDamageFactor": 0
                        },
                        "armor_2": {
                            "vehicleDamageFactor": 0
                        },
                        "armor_3": {
                            "vehicleDamageFactor": 0
                        },
                        "armor_4": {
                            "vehicleDamageFactor": 0
                        },
                        "gun": 50
                    },
                    "pitchLimits": {
                        "minPitch": [
                            0.0,
                            -20.0,
                            1.0,
                            -20.0
                        ],
                        "maxPitch": [
                            0.0,
                            7.0,
                            1.0,
                            7.0
                        ]
                    },
                    "turretYawLimits": [
                        -136.0,
                        136.0
                    ],
                    "reloadTime": 8.6,
                    "shotDispersionFactors": {
                        "turretRotation": 0.06,
                        "afterShot": 4.0,
                        "whileGunDamaged": 2.0
                    },
                    "shotDispersionRadius": 0.4,
                    "aimingTime": 1.7,
                    "invisibilityFactorAtShot": 0.18,
                    "models": {
                        "undamaged": "vehicles/american/A151_TS_60/normal/lod0/Gun_01.model",
                        "destroyed": "vehicles/american/A151_TS_60/crash/lod0/Gun_01.model",
                        "exploded": "vehicles/american/A151_TS_60/crash/lod0/Gun_01.model"
                    },
                    "hitTester": {
                        "collisionModelServer": "vehicles/american/A151_TS_60/collision/Gun_01.model",
                        "collisionModelClient": "vehicles/american/A151_TS_60/collision_client/Gun_01.model"
                    },
                    "customizationSlots": {
                        "slot": {
                            "slotType": "insigniaOnGun",
                            "slotId": 49000,
                            "rayStart": [
                                0.000577,
                                0.003825,
                                3.66495
                            ],
                            "rayEnd": [
                                0.000577,
                                0.003825,
                                4.355575
                            ],
                            "rayUp": [
                                0.119375,
                                0.0,
                                0.0
                            ],
                            "size": 0.690625
                        }
                    },
                    "customization": {
                        "customizableVehicleAreas": {
                            "paint": [
                                "GUN",
                                "GUN_2"
                            ],
                            "camouflage": "GUN"
                        }
                    },
                    "camouflage": {
                        "density": [
                            166.934,
                            170.079
                        ],
                        "aoTextureSize": [
                            512.0,
                            512.0
                        ]
                    }
                }
            },
            "models": {
                "undamaged": "vehicles/american/A151_TS_60/normal/lod0/Turret_01.model",
                "destroyed": "vehicles/american/A151_TS_60/crash/lod0/Turret_01.model",
                "exploded": "vehicles/american/A151_TS_60/crash/lod0/Turret_01.model"
            },
            "hitTester": {
                "collisionModelServer": "vehicles/american/A151_TS_60/collision/Turret_01.model",
                "collisionModelClient": "vehicles/american/A151_TS_60/collision_client/Turret_01.model"
            },
            "gunPosition": [
                0.0,
                0.495828,
                1.60034
            ],
            "wwturretRotatorSoundManual": "tur_mech_trav",
            "physicsShape": [
                1.014,
                0.0,
                1.0,
                0.0,
                0.769,
                -0.074,
                0.693,
                0.407,
                0.71,
                0.5,
                0.0,
                0.5,
                0.016,
                0.0,
                0.001
            ],
            "customizationSlots": {
                "slot": {
                    "slotType": "projectionDecal",
                    "slotId": 35036,
                    "tags": [
                        "formfactor_rect1x2",
                        "cover",
                        "direction_right_to_left"
                    ],
                    "position": [
                        1.6e-05,
                        2.16447,
                        0.490492
                    ],
                    "rotation": [
                        -9e-06,
                        -1.56905,
                        2.91255
                    ],
                    "scale": [
                        6.66575,
                        3.99999,
                        6.66574
                    ],
                    "hiddenForUser": "true",
                    "showOn": 4368,
                    "clipAngle": 0.600127,
                    "anchorShift": 0.228501
                }
            },
            "customization": {
                "customizableVehicleAreas": {
                    "paint": "TURRET",
                    "camouflage": "TURRET"
                }
            },
            "camouflage": {
                "density": [
                    95.1892,
                    95.5822
                ],
                "aoTextureSize": [
                    512.0,
                    512.0
                ]
            }
        }
    },
    "engines": {
        "Continental_AVI_1790_8P": "shared"
    },
    "fuelTanks": {
        "Heavy": "shared"
    },
    "radios": {
        "AN_GRC_7A": "shared"
    },
    "clientAdjustmentFactors": null,
    "physics": {
        "detailed": {
            "engines": {
                "Continental_AVI_1790_8P": {
                    "smplEnginePower": 800,
                    "smplFwMaxSpeed": 35
                }
            },
            "chassis": {
                "Chassis_A151_TS_60": {
                    "axleCount": 5,
                    "grounds": {
                        "soft": {
                            "rollingFriction": 0.23345
                        },
                        "medium": {
                            "rollingFriction": 0.1127
                        },
                        "firm": {
                            "rollingFriction": 0.08855
                        }
                    }
                }
            }
        }
    },
    "effects": {
        "collision": null,
        "damagedStateGroup": "large"
    },
    "emblems": {
        "default": 15503,
        "lodDist": "MEDIUM",
        "alpha": 0.88
    }
}